{
  "kind": "youtube#video",
  "etag": "8fMgKAAaU-xugEJ5ckuUHGtzATA",
  "id": "kOPICPQBqSE",
  "snippet": {
    "publishedAt": "2026-02-02T23:17:02Z",
    "channelId": "UCWJ5MfdQZ6jXbF5gYuSAf5Q",
    "title": "Stranger Things: Tales From ‘85 - Official Teaser Trailer (2026) Brooklyn Davey Norstedt",
    "description": "Check out Stranger Things: Tales From ‘85 teaser trailer for this upcoming animated series from Showrunner Eric Robles and Executive Producers the Duffer Brothers. Stranger Things: Tales From '85 features Brooklyn Davey Norstedt as Eleven, Jolie Hoang-Rappaport as Max, Luca Diaz as Mike, Elisha “EJ” Williams as Lucas, Braxton Quinney as Dustin, Benjamin Plessala as Will, Brett Gipson as Hopper, Jeremy Jordan as Steve, Odessa A’zion, Janeane Garofalo and Lou Diamond Phillips.\n\nIn the winter of 1985, snow blankets the town and the horrors of the Upside Down are finally fading. Our heroes Eleven, Mike, Will, Dustin, Lucas, and Max have settled back into a normal life of D&D, snowball fights, and quiet days. But beneath the ice, something terrifying has awakened. Could it be from the Upside Down? From the depths of Hawkins Lab? Or from somewhere else entirely? Our heroes must race to solve this mystery and save Hawkins in this untold story set in the Stranger Things universe.\n\nEric Robles is the showrunner & executive producer on Stranger Things: Tales From ‘85. Matt and Ross Duffer, along with Hilary Leavitt, via Upside Down Pictures; Shawn Levy via 21 Laps; Dan Cohen serve as executive producers. The animation studio is Flying Bark Productions. \n\nStranger Things: Tales From ’85 premieres April 23 on Netflix.\n\n#StrangerThingsTalesFrom85 #StrangerThings #IGN",
    "thumbnails": {
      "default": {
        "url": "https://i.ytimg.com/vi/kOPICPQBqSE/default.jpg",
        "width": 120,
        "height": 90
      },
      "medium": {
        "url": "https://i.ytimg.com/vi/kOPICPQBqSE/mqdefault.jpg",
        "width": 320,
        "height": 180
      },
      "high": {
        "url": "https://i.ytimg.com/vi/kOPICPQBqSE/hqdefault.jpg",
        "width": 480,
        "height": 360
      },
      "standard": {
        "url": "https://i.ytimg.com/vi/kOPICPQBqSE/sddefault.jpg",
        "width": 640,
        "height": 480
      },
      "maxres": {
        "url": "https://i.ytimg.com/vi/kOPICPQBqSE/maxresdefault.jpg",
        "width": 1280,
        "height": 720
      }
    },
    "channelTitle": "IGN Movie Trailers",
    "tags": [
      "Stranger Things",
      "Stranger Things: Tales From '85",
      "stranger things: tales from ‘85",
      "stranger things tales from 85",
      "stranger things tales from 85 trailer",
      "stranger things tales from 85 teaser",
      "stranger things animated series",
      "tales from 85",
      "stranger things 5 trailer",
      "stranger things: tales from ’85",
      "stranger things tales from 85 release date",
      "stranger things: tales from '85",
      "stranger things tales from ‘85",
      "stranger things tales from '85 trailer",
      "stranger things spinoff"
    ],
    "categoryId": "24",
    "liveBroadcastContent": "none",
    "defaultLanguage": "en",
    "localized": {
      "title": "Stranger Things: Tales From ‘85 - Official Teaser Trailer (2026) Brooklyn Davey Norstedt",
      "description": "Check out Stranger Things: Tales From ‘85 teaser trailer for this upcoming animated series from Showrunner Eric Robles and Executive Producers the Duffer Brothers. Stranger Things: Tales From '85 features Brooklyn Davey Norstedt as Eleven, Jolie Hoang-Rappaport as Max, Luca Diaz as Mike, Elisha “EJ” Williams as Lucas, Braxton Quinney as Dustin, Benjamin Plessala as Will, Brett Gipson as Hopper, Jeremy Jordan as Steve, Odessa A’zion, Janeane Garofalo and Lou Diamond Phillips.\n\nIn the winter of 1985, snow blankets the town and the horrors of the Upside Down are finally fading. Our heroes Eleven, Mike, Will, Dustin, Lucas, and Max have settled back into a normal life of D&D, snowball fights, and quiet days. But beneath the ice, something terrifying has awakened. Could it be from the Upside Down? From the depths of Hawkins Lab? Or from somewhere else entirely? Our heroes must race to solve this mystery and save Hawkins in this untold story set in the Stranger Things universe.\n\nEric Robles is the showrunner & executive producer on Stranger Things: Tales From ‘85. Matt and Ross Duffer, along with Hilary Leavitt, via Upside Down Pictures; Shawn Levy via 21 Laps; Dan Cohen serve as executive producers. The animation studio is Flying Bark Productions. \n\nStranger Things: Tales From ’85 premieres April 23 on Netflix.\n\n#StrangerThingsTalesFrom85 #StrangerThings #IGN"
    },
    "defaultAudioLanguage": "en"
  },
  "contentDetails": {
    "duration": "PT1M50S",
    "dimension": "2d",
    "definition": "hd",
    "caption": "false",
    "licensedContent": true,
    "contentRating": {},
    "projection": "rectangular"
  },
  "statistics": {
    "viewCount": "389",
    "likeCount": "34",
    "favoriteCount": "0",
    "commentCount": "2"
  }
}