{
  "kind": "youtube#video",
  "etag": "i6ESI8oLcgaoWSrWqe5pOHoU3oM",
  "id": "vNm8cuVGpnc",
  "snippet": {
    "publishedAt": "2026-02-02T17:45:06Z",
    "channelId": "UC6LDwTYRfjQwkakw5R95OyA",
    "title": "Crazy Night Out Scene | GROUNDHOG DAY (1993) Movie CLIP 4K",
    "description": "Watch Now: https://www.sonypictures.com/movies/groundhogday\n\nBuy Now: https://www.amazon.com/exec/obidos/ASIN/B07CLW1R17/joblosmovieempor/\n\nA cynical TV weatherman finds himself reliving the same day over and over again when he goes on location to the small town of Punxsutawney to film a report about their annual Groundhog Day. His predicament drives him to distraction, until he sees a way of turning the situation to his advantage.\n\nWanna support us? Get your JoBlo Merch right here!\nhttps://joblo-merch.creator-spring.com/\n\nSUBSCRIBE for more all the latest Movie Clips here: https://www.youtube.com/@JoBloMovieClips?sub_confirmation=1\n\nFootage Courtesy Of Sony Pictures Entertainment Inc.\n\n#GroundhogDay",
    "thumbnails": {
      "default": {
        "url": "https://i.ytimg.com/vi/vNm8cuVGpnc/default.jpg",
        "width": 120,
        "height": 90
      },
      "medium": {
        "url": "https://i.ytimg.com/vi/vNm8cuVGpnc/mqdefault.jpg",
        "width": 320,
        "height": 180
      },
      "high": {
        "url": "https://i.ytimg.com/vi/vNm8cuVGpnc/hqdefault.jpg",
        "width": 480,
        "height": 360
      },
      "standard": {
        "url": "https://i.ytimg.com/vi/vNm8cuVGpnc/sddefault.jpg",
        "width": 640,
        "height": 480
      },
      "maxres": {
        "url": "https://i.ytimg.com/vi/vNm8cuVGpnc/maxresdefault.jpg",
        "width": 1280,
        "height": 720
      }
    },
    "channelTitle": "JoBlo Movie Clips",
    "tags": [
      "movie clips",
      "movie clip",
      "joblo movie clips",
      "movieclips",
      "clip compilation",
      "JoBlo Movie Clips",
      "JoBlo clips",
      "JoBlo movie",
      "Joblo",
      "Jo Blo",
      "Celebrity workout routines",
      "Celebrity cooking and recipes",
      "Celebrity travel vlogs",
      "4K",
      "groundhog day",
      "groundhog day 1993",
      "bill murray",
      "groundhog day scene",
      "movie scene",
      "classic movie",
      "comedy movie",
      "90s movie",
      "time loop",
      "groundhog day 4k",
      "phil connors",
      "groundhog day moment",
      "iconic movie scene",
      "classic film",
      "comedy scene"
    ],
    "categoryId": "1",
    "liveBroadcastContent": "none",
    "defaultLanguage": "en",
    "localized": {
      "title": "Crazy Night Out Scene | GROUNDHOG DAY (1993) Movie CLIP 4K",
      "description": "Watch Now: https://www.sonypictures.com/movies/groundhogday\n\nBuy Now: https://www.amazon.com/exec/obidos/ASIN/B07CLW1R17/joblosmovieempor/\n\nA cynical TV weatherman finds himself reliving the same day over and over again when he goes on location to the small town of Punxsutawney to film a report about their annual Groundhog Day. His predicament drives him to distraction, until he sees a way of turning the situation to his advantage.\n\nWanna support us? Get your JoBlo Merch right here!\nhttps://joblo-merch.creator-spring.com/\n\nSUBSCRIBE for more all the latest Movie Clips here: https://www.youtube.com/@JoBloMovieClips?sub_confirmation=1\n\nFootage Courtesy Of Sony Pictures Entertainment Inc.\n\n#GroundhogDay"
    },
    "defaultAudioLanguage": "en-US"
  },
  "contentDetails": {
    "duration": "PT4M29S",
    "dimension": "2d",
    "definition": "hd",
    "caption": "false",
    "licensedContent": true,
    "contentRating": {},
    "projection": "rectangular"
  },
  "statistics": {
    "viewCount": "1657",
    "likeCount": "56",
    "favoriteCount": "0",
    "commentCount": "2"
  }
}